{
  "success":"成功",
  "data":{
    "pageStart":0,
    "pageSize":6,
    "count":10,
    "list":[{
      "creatAt":"2018-03-8",
      "creatByFullName":"管理员",
      "describe":"狄更斯曾说过：“天下最苦恼的事莫过于看不起自己的家”，家装是一件大事，很多人在购房之后都会考虑到装修大事，装修的好坏会影响到很多方面。老张进入家装行业已经十几年，如今他搭建了一个完全免费的连接用户与商家的平台，帮助用户省钱省事装好房，他觉得，这是让他最开心的事了。",
      "title":"老张：看着你们装修被坑，我心疼啊！",
      "sysId":1,
      "coverImg":"imgs/listImg/list_imgTa01.jpg",
      "status":2
    },{
      "creatAt":"2017-04-10",
      "creatByFullName":"管理员",
      "describe":"April觉得自己是个奇怪的人，尚且年纪轻轻，却常常想去养鸡养花种西瓜，觉得非得这样，才算像样的生活。草长久了就要拔，17年春天，她辞去电商公司运营的工作回到南京，结束异地恋，开始尝试向往的生活方式。春天是万物萌芽的季节，April关于美好生活的实践也开始萌芽了。",
      "title":"April：做全职的生活者",
      "sysId":2,
      "coverImg":"imgs/listImg/list_imgTa02.jpg",
      "status":2
    },{
      "creatAt":"2017-03-28",
      "creatByFullName":"管理员",
      "describe":"阿豆现在是一名风光摄影师、商业修图师，几个月前，这个“不安分”的少年刚辞去了国企的工作，背起行囊，踏上了北漂的路。",
      "title":"阿豆：未知才是做美好的事",
      "sysId":3,
      "coverImg":"imgs/listImg/list_imgTa03.jpg",
      "status":2
    },{
      "creatAt":"2017-05-06",
      "creatByFullName":"管理员",
      "describe":"从抱着金庸的小说沉迷在武侠世界里，到看着那些武打明星将武侠世界搬到银屏之上。大抵所有男人心中都藏着一个义薄云天的“乔峰”大哥，也都渴望拥有一份如小龙女和杨过般的美满真情。",
      "title":"张小蝶：上山下海搞平台",
      "sysId":4,
      "coverImg":"imgs/listImg/list_imgTa04.jpg",
      "status":2
    },{
      "creatAt":"2017-06-01",
      "creatByFullName":"管理员",
      "describe":"南京地铁四号线的卡通IP人物“阿紫”和公众见面那天，小晓作为真人版的“小阿紫”也一同亮相。那天小晓穿了一身民国风的紫色裙子，头戴紫色发箍，在咔擦咔擦的闪光下笑得稚嫩又可爱。",
      "title":"孙小晓",
      "sysId":5,
      "coverImg":"imgs/listImg/list_imgTa05.jpg",
      "status":2
    },{
      "creatAt":"2017-06-02",
      "creatByFullName":"管理员",
      "describe":"张君雅小妹妹是土生土长的杭州人，皮肤白皙，身材纤瘦，确有江南女子的温婉。但是，和她相处久了，就会发现她骨子里的那股子拼劲真的很令人佩服。也许正是是因为这股劲一直推动着她，让她对自己的作品一直要求精益求精。",
      "title":"张君雅小妹妹：做自己的手作，走自己的路",
      "sysId":6,
      "coverImg":"imgs/listImg/list_imgTa06.jpg",
      "status":2
    },{
      "creatAt":"2017-06-03",
      "creatByFullName":"管理员",
      "describe":"李照清这个名字，乍一见总让人以为是李清照。一句“知否知否，应是绿肥红瘦”里藏了几多少女的心事，再加上李照清的古筝专业，总让人不相识她的人一厢情愿地以为她是个文文弱弱多愁善感的女孩子。",
      "title":"李照清：最简单的快乐就是小确幸",
      "sysId":7,
      "coverImg":"imgs/listImg/list_imgTa07.jpg",
      "status":2
    },{
      "creatAt":"2017-06-06",
      "creatByFullName":"管理员",
      "describe":"Grace，一个曾经做建筑设计咨询的女子，最终选择以经营宠物店为终身职业。",
      "title":"Grace：宠爱一生",
      "sysId":8,
      "coverImg":"imgs/listImg/list_imgTa08.jpg",
      "status":2
    },{
      "creatAt":"2017-06-07",
      "creatByFullName":"管理员",
      "describe":"“我08年来南京上大学，现在在读博，在南京待了也将近10年了。我的人生没有几个十年，一个女生最美的10年，就在南京度过了。”肖千璐说。",
      "title":"肖千璐：女博士的南京十年",
      "sysId":9,
      "coverImg":"imgs/listImg/list_imgTa09.jpg",
      "status":2
    },{
      "creatAt":"2017-06-08",
      "creatByFullName":"管理员",
      "describe":"“虽然是个看起来普通得不能再普通的小理想，可是过程中还是会遇到很多麻烦，不过我相信我总有一天会实现它的……”",
      "title":"庄园：三餐四季，厨房与爱",
      "sysId":10,
      "coverImg":"imgs/listImg/list_imgTa10.jpg",
      "status":2
    }
    ]
  }
}